MANIFEST.in
README.txt
setup.py
rtcsig/__init__.py
rtcsig/urls.py
rtcsig/views.py
rtcsig.egg-info/PKG-INFO
rtcsig.egg-info/SOURCES.txt
rtcsig.egg-info/dependency_links.txt
rtcsig.egg-info/not-zip-safe
rtcsig.egg-info/requires.txt
rtcsig.egg-info/top_level.txt
static/js/rtc.js