Metadata-Version: 1.1
Name: rtcsig
Version: 0.2
Summary: This is a Django App for handle the session exchanging of a WebRTC peer interconnection
Home-page: https://github.com/maurostorch/rtcsig
Author: Mauro Storch
Author-email: mauro@storchlab.com
License: The MIT License (MIT)
Platform: UNKNOWN
Classifier: Development Status :: 3 - Alpha
Classifier: Operating System :: OS Independent
Classifier: Programming Language :: Python :: 2
Classifier: Programming Language :: Python :: 2.7
Classifier: License :: OSI Approved :: MIT License
Classifier: Topic :: Communications
Classifier: Topic :: Communications :: File Sharing
Classifier: Framework :: Django
